{
    "name": "Security Quiz",
    "logoUrl": "./img/logo.svg",
    "logoWidth": "250px",
    "logoHeight": "100px",
    "description": "This quiz is designed to help you think about digital habits that you have, how these impact your digital security, and how to improve habits that leave you vulnerable.",
    "questions": [
        {
            "questionContent": "I usually perform virus and malware scans on my computer…",
            "questionCategory": "catHardware",
            "questionAnswers": [
                {
                    "answerContent": "Never",
                    "answerValue": 400
                }, {
                    "answerContent": "Rarely, once a year or so",
                    "answerValue": 300
                }, {
                    "answerContent": "Sometimes, once every few months",
                    "answerValue": 200
                }, {
                    "answerContent": "Often, once every month",
                    "answerValue": 100
                }
            ]
        }, {
            "questionContent": "Do you use an adblocker?",
            "questionCategory": "catBrowser",
            "questionAnswers": [
                {
                    "answerContent": "Yes, when I can.",
                    "answerValue": 100
                }, {
                    "answerContent": "No.",
                    "answerValue": 200
                }
            ]
        }, {
            "questionContent": "I use truthful answers for security questions. (ie \"What was your first pet's name?\")",
            "questionCategory": "catAuth",
            "questionAnswers": [
                {
                    "answerContent": "Yes",
                    "answerValue": 100
                }, {
                    "answerContent": "No",
                    "answerValue": 200
                }
            ]
        }, {
            "questionContent": "I use multifactor authentication to log into various online accounts",
            "questionCategory": "catAuth",
            "questionAnswers": [
                {
                    "answerContent": "Yes",
                    "answerValue": 100
                }, {
                    "answerContent": "No",
                    "answerValue": 200
                }, {
                    "answerContent": "What is multifactor authentication…?",
                    "answerValue": 300
                }
            ]
        }, {
            "questionContent": "I deactivate accounts for websites and services that I no longer use.",
            "questionCategory": "catAccounts",
            "questionAnswers": [
                {
                    "answerContent": "Yes",
                    "answerValue": 100
                }, {
                    "answerContent": "No",
                    "answerValue": 200
                }
            ]
        }, {
            "questionContent": "The last time I checked privacy settings for my social media accounts was…",
            "questionCategory": "catSocial",
            "questionAnswers": [
                {
                    "answerContent": "Within 1 month ago",
                    "answerValue": 100
                }, {
                    "answerContent": "1-3 months ago",
                    "answerValue": 200
                }, {
                    "answerContent": "3-6 months ago",
                    "answerValue": 300
                }, {
                    "answerContent": "More than half a year ago",
                    "answerValue": 400
                }
            ]
        }, {
            "questionContent": "I use unique passwords...",
            "questionCategory": "catAuth",
            "questionAnswers": [
                {
                    "answerContent": "For every website.",
                    "answerImage": "an image",
                    "answerValue": 100
                }, {
                    "answerContent": "For important websites only. (Banking, email, etc.)",
                    "answerImage": "False",
                    "answerValue": 200
                }, {
                    "answerContent": "All my passwords are the same.",
                    "answerImage": "False",
                    "answerValue": 300
                }
            ]
        }, {
            "questionContent": "Do you have a physical cover on your webcam (or, do you unplug your webcam when not in use)?",
            "questionImage": "http://via.placeholder.com/1000x350",
            "questionCategory": "catHardware",
            "questionAnswers": [
                {
                    "answerContent": "Yes",
                    "answerImage": "an image",
                    "answerValue": 100
                }, {
                    "answerContent": "No",
                    "answerImage": "False",
                    "answerValue": 200
                }
            ]
        }, {
            "questionContent": "I check my browser extensions and plugins...",
            "questionImage": "http://via.placeholder.com/1000x350",
            "questionCategory": "catBrowser",
            "questionAnswers": [
                {
                    "answerContent": "Every day",
                    "answerValue": 400
                }, {
                    "answerContent": "Once a week",
                    "answerValue": 300
                }, {
                    "answerContent": "Once a month",
                    "answerValue": 200
                }, {
                    "answerContent": "Never",
                    "answerValue": 100
                }
            ]
        }, {
            "questionContent": "I post pictures of my vacations on social media.",
            "questionImage": "http://via.placeholder.com/1000x350",
            "questionCategory": "catSocial",
            "questionAnswers": [
                {
                    "answerContent": "Yes, but after I've returned home.",
                    "answerImage": "an image",
                    "answerValue": 100
                }, {
                    "answerContent": "Yes, while I'm on vacation.",
                    "answerImage": "False",
                    "answerValue": 200
                }, {
                    "answerContent": "No.",
                    "answerImage": "False",
                    "answerValue": 300
                }
            ]
        }
    ],
    "lessons": [
        {
            "title": "Authentication",
            "content": {
                "what": "Authentication is a series of steps (like password entry) designed to ensure people signing into accounts are who they say they are.",
                "why": "Authentication makes sure that users only access what they're supposed to and data is protected.",
                "action": "Use multi-factor authentication and make sure your passwords are strong and not used across the same websites.",
                "more": [
                    {
                        "name": "How to Create Stronger Passwords",
                        "url": "https://support.google.com/accounts/answer/32040?hl=en",
                        "description": "3 steps you can take."
                    },
                    {
                        "name": "What is 2FA?",
                        "url": "https://www.securenvoy.com/two-factor-authentication/what-is-2fa.shtm",
                        "description": "an introduction to multifactor/two factor authentication and how to enable it."
                    }
                ]
            }
        }, {
            "title": "Online Accounts",
            "content": {
                "what": "Lorem ipsum dolor sit amet",
                "why": "Lorem ipsum dolor sit amet",
                "action": "Lorem ipsum dolor sit amet",
                "more": [
                    {
                        "name": "Link",
                        "url": "#",
                        "description": "Lorem ipsum dolor sit amet"
                    }
                ]
            }
        }, {
            "title": "The Browser",
            "content": {
                "what": "Lorem ipsum dolor sit amet",
                "why": "Lorem ipsum dolor sit amet",
                "action": "Lorem ipsum dolor sit amet",
                "more": [
                    {
                        "name": "Link",
                        "url": "#",
                        "description": "Lorem ipsum dolor sit amet"
                    }
                ]
            }
        }, {
            "title": "Hardware",
            "content": {
                "what": "Lorem ipsum dolor sit amet",
                "why": "Lorem ipsum dolor sit amet",
                "action": "Lorem ipsum dolor sit amet",
                "more": [
                    {
                        "name": "Link",
                        "url": "#",
                        "description": "Lorem ipsum dolor sit amet"
                    }
                ]
            }
        }, {
            "title": "Social Media",
            "content": {
                "what": "Lorem ipsum dolor sit amet",
                "why": "Lorem ipsum dolor sit amet",
                "action": "Lorem ipsum dolor sit amet",
                "more": [
                    {
                        "name": "Link",
                        "url": "#",
                        "description": "Lorem ipsum dolor sit amet"
                    }
                ]
            }
        }
    ]
}
